Metadata-Version: 1.0
Name: My-Test-Project-Rawa
Version: 0.2.0
Summary: Python command line application bare bones template.
Home-page: http://gehrcke.de/2014/02/distributing-a-python-command-line-application
Author: Jan-Philip Gehrcke
Author-email: jgehrcke@googlemail.com
License: UNKNOWN
Platform: UNKNOWN
